{"Symbol":"AMZN","AnalyzedTransactions":[{"SecurityTitle":"Common stock, par value $.01 per share","SecuritiesOwnedFollowingTransaction":97.0,"DirectOrIndirectOwnership":0,"TransactionDate":"2011-11-04T00:00:00","TransactionCode":0,"TransactionQuantity":97.0,"TransactionPricePerSecurity":217.6691,"AcquiredOrDisposed":0},{"SecurityTitle":"Common stock, par value $.01 per share","SecuritiesOwnedFollowingTransaction":1831.0,"DirectOrIndirectOwnership":0,"TransactionDate":"2012-01-12T00:00:00","TransactionCode":0,"TransactionQuantity":68.0,"TransactionPricePerSecurity":177.2319,"AcquiredOrDisposed":0},{"SecurityTitle":"Common Stock, par value $.01 per share","SecuritiesOwnedFollowingTransaction":250.0,"DirectOrIndirectOwnership":0,"TransactionDate":"2019-10-04T00:00:00","TransactionCode":0,"TransactionQuantity":100.0,"TransactionPricePerSecurity":1726.06,"AcquiredOrDisposed":0}],"AveragePerformance":{"Beginning":"2010-01-01T00:00:00","End":"2019-12-31T00:00:00","Return14":0.01009743,"Return30":0.021762256,"Return90":0.06671786,"Return180":0.137887,"Return360":0.2947868},"PerformancesFollowingInsiderBuys":[{"Beginning":"2011-11-04T00:00:00","End":"2012-11-04T00:00:00","Return14":-0.08933849,"Return30":-0.09349589,"Return90":-0.16056909,"Return180":0.06360867,"Return360":0.07580379},{"Beginning":"2012-01-12T00:00:00","End":"2013-01-12T00:00:00","Return14":0.09884622,"Return30":0.054624002,"Return90":0.06843636,"Return180":0.24765538,"Return360":0.5259478},{"Beginning":"2019-10-04T00:00:00","End":"2020-10-04T00:00:00","Return14":0.010266424,"Return30":0.03736959,"Return90":0.09102979,"Return180":0.09659985,"Return360":0.8245337}]}