{"Symbol":"HSY","AnalyzedTransactions":[{"SecurityTitle":"Common Stock","SecuritiesOwnedFollowingTransaction":2622.358,"DirectOrIndirectOwnership":0,"TransactionDate":"2012-02-27T00:00:00","TransactionCode":0,"TransactionQuantity":500.0,"TransactionPricePerSecurity":60.75,"AcquiredOrDisposed":0},{"SecurityTitle":"Common Stock, $1.00 par value","SecuritiesOwnedFollowingTransaction":12703821.0,"DirectOrIndirectOwnership":0,"TransactionDate":"2015-11-13T00:00:00","TransactionCode":0,"TransactionQuantity":190000.0,"TransactionPricePerSecurity":83.82,"AcquiredOrDisposed":0},{"SecurityTitle":"Common Stock, $1.00 par value","SecuritiesOwnedFollowingTransaction":12703821.0,"DirectOrIndirectOwnership":1,"TransactionDate":"2015-11-13T00:00:00","TransactionCode":0,"TransactionQuantity":190000.0,"TransactionPricePerSecurity":83.82,"AcquiredOrDisposed":0},{"SecurityTitle":"Common Stock, $1.00 par value","SecuritiesOwnedFollowingTransaction":12753421.0,"DirectOrIndirectOwnership":0,"TransactionDate":"2016-11-07T00:00:00","TransactionCode":0,"TransactionQuantity":49500.0,"TransactionPricePerSecurity":101.6,"AcquiredOrDisposed":0},{"SecurityTitle":"Common Stock, $1.00 par value","SecuritiesOwnedFollowingTransaction":12753421.0,"DirectOrIndirectOwnership":1,"TransactionDate":"2016-11-07T00:00:00","TransactionCode":0,"TransactionQuantity":49500.0,"TransactionPricePerSecurity":101.6,"AcquiredOrDisposed":0},{"SecurityTitle":"Common Stock, par value $0.0001 per share","SecuritiesOwnedFollowingTransaction":1000.0,"DirectOrIndirectOwnership":0,"TransactionDate":"2018-01-31T00:00:00","TransactionCode":0,"TransactionQuantity":76739900.0,"TransactionPricePerSecurity":12.0,"AcquiredOrDisposed":0},{"SecurityTitle":"Common Stock, $1.00 par value","SecuritiesOwnedFollowingTransaction":8300791.0,"DirectOrIndirectOwnership":0,"TransactionDate":"2018-10-29T00:00:00","TransactionCode":0,"TransactionQuantity":47170.0,"TransactionPricePerSecurity":106.0,"AcquiredOrDisposed":0},{"SecurityTitle":"Common Stock, $1.00 par value","SecuritiesOwnedFollowingTransaction":8300791.0,"DirectOrIndirectOwnership":1,"TransactionDate":"2018-10-29T00:00:00","TransactionCode":0,"TransactionQuantity":47170.0,"TransactionPricePerSecurity":106.0,"AcquiredOrDisposed":0},{"SecurityTitle":"Common Stock","SecuritiesOwnedFollowingTransaction":10878.0,"DirectOrIndirectOwnership":0,"TransactionDate":"2018-11-06T00:00:00","TransactionCode":0,"TransactionQuantity":2000.0,"TransactionPricePerSecurity":107.32,"AcquiredOrDisposed":0},{"SecurityTitle":"Common Stock","SecuritiesOwnedFollowingTransaction":4761.0,"DirectOrIndirectOwnership":0,"TransactionDate":"2019-05-30T00:00:00","TransactionCode":0,"TransactionQuantity":100.0,"TransactionPricePerSecurity":130.096,"AcquiredOrDisposed":0},{"SecurityTitle":"Common Stock","SecuritiesOwnedFollowingTransaction":15773.324,"DirectOrIndirectOwnership":0,"TransactionDate":"2019-05-30T00:00:00","TransactionCode":0,"TransactionQuantity":2000.0,"TransactionPricePerSecurity":129.92,"AcquiredOrDisposed":0},{"SecurityTitle":"Common Stock","SecuritiesOwnedFollowingTransaction":1000.0,"DirectOrIndirectOwnership":0,"TransactionDate":"2019-05-31T00:00:00","TransactionCode":0,"TransactionQuantity":1000.0,"TransactionPricePerSecurity":129.14,"AcquiredOrDisposed":0}],"AveragePerformance":{"Beginning":"2010-01-01T00:00:00","End":"2019-12-31T00:00:00","Return14":0.00635614,"Return30":0.013669785,"Return90":0.0415725,"Return180":0.08487327,"Return360":0.17695001},"PerformancesFollowingInsiderBuys":[{"Beginning":"2012-02-27T00:00:00","End":"2013-02-27T00:00:00","Return14":0.0034799445,"Return30":0.0092794895,"Return90":0.12843639,"Return180":0.21629757,"Return360":0.36000508},{"Beginning":"2015-11-13T00:00:00","End":"2016-11-13T00:00:00","Return14":0.045141507,"Return30":0.08009983,"Return90":0.063041225,"Return180":0.11528699,"Return360":0.24314678},{"Beginning":"2015-11-13T00:00:00","End":"2016-11-13T00:00:00","Return14":0.045141507,"Return30":0.08009983,"Return90":0.063041225,"Return180":0.11528699,"Return360":0.24314678},{"Beginning":"2016-11-07T00:00:00","End":"2017-11-07T00:00:00","Return14":-0.031426582,"Return30":-0.017857142,"Return90":0.063856,"Return180":0.07134571,"Return360":0.07417272},{"Beginning":"2016-11-07T00:00:00","End":"2017-11-07T00:00:00","Return14":-0.031426582,"Return30":-0.017857142,"Return90":0.063856,"Return180":0.07134571,"Return360":0.07417272},{"Beginning":"2018-01-31T00:00:00","End":"2019-01-31T00:00:00","Return14":-0.102510765,"Return30":-0.09782446,"Return90":-0.1667172,"Return180":-0.101186186,"Return360":-0.02801514},{"Beginning":"2018-10-29T00:00:00","End":"2019-10-29T00:00:00","Return14":0.025188701,"Return30":0.012881542,"Return90":-0.003263818,"Return180":0.19657606,"Return360":0.4138528},{"Beginning":"2018-10-29T00:00:00","End":"2019-10-29T00:00:00","Return14":0.025188701,"Return30":0.012881542,"Return90":-0.003263818,"Return180":0.19657606,"Return360":0.4138528},{"Beginning":"2018-11-06T00:00:00","End":"2019-11-06T00:00:00","Return14":-0.004603101,"Return30":0.010914819,"Return90":-0.01161419,"Return180":0.1634014,"Return360":0.3602891},{"Beginning":"2019-05-30T00:00:00","End":"2020-05-30T00:00:00","Return14":0.052136745,"Return30":0.02461578,"Return90":0.23282045,"Return180":0.15515058,"Return360":0.016739868},{"Beginning":"2019-05-30T00:00:00","End":"2020-05-30T00:00:00","Return14":0.052136745,"Return30":0.02461578,"Return90":0.23282045,"Return180":0.15515058,"Return360":0.016739868},{"Beginning":"2019-05-31T00:00:00","End":"2020-05-31T00:00:00","Return14":0.04819653,"Return30":0.017353665,"Return90":0.20311494,"Return180":0.13719927,"Return360":-0.007518292}]}