{"Symbol":"MCD","AnalyzedTransactions":[{"SecurityTitle":"Common Stock","SecuritiesOwnedFollowingTransaction":12184.0,"DirectOrIndirectOwnership":0,"TransactionDate":"2012-06-11T00:00:00","TransactionCode":0,"TransactionQuantity":650.0,"TransactionPricePerSecurity":87.53,"AcquiredOrDisposed":0},{"SecurityTitle":"Common Stock","SecuritiesOwnedFollowingTransaction":2288.0,"DirectOrIndirectOwnership":0,"TransactionDate":"2012-11-07T00:00:00","TransactionCode":0,"TransactionQuantity":288.0,"TransactionPricePerSecurity":87.16,"AcquiredOrDisposed":0},{"SecurityTitle":"Common Stock","SecuritiesOwnedFollowingTransaction":5919.0,"DirectOrIndirectOwnership":0,"TransactionDate":"2013-10-25T00:00:00","TransactionCode":0,"TransactionQuantity":425.0,"TransactionPricePerSecurity":94.707,"AcquiredOrDisposed":0},{"SecurityTitle":"Common Stock","SecuritiesOwnedFollowingTransaction":2130.0,"DirectOrIndirectOwnership":1,"TransactionDate":"2016-02-10T00:00:00","TransactionCode":0,"TransactionQuantity":2130.0,"TransactionPricePerSecurity":117.7,"AcquiredOrDisposed":0},{"SecurityTitle":"Common Stock","SecuritiesOwnedFollowingTransaction":1600.0,"DirectOrIndirectOwnership":0,"TransactionDate":"2017-03-22T00:00:00","TransactionCode":0,"TransactionQuantity":1600.0,"TransactionPricePerSecurity":128.942,"AcquiredOrDisposed":0},{"SecurityTitle":"Common Stock","SecuritiesOwnedFollowingTransaction":2900.0,"DirectOrIndirectOwnership":0,"TransactionDate":"2019-11-06T00:00:00","TransactionCode":0,"TransactionQuantity":1300.0,"TransactionPricePerSecurity":193.46,"AcquiredOrDisposed":0},{"SecurityTitle":"Common Stock","SecuritiesOwnedFollowingTransaction":2580.0,"DirectOrIndirectOwnership":0,"TransactionDate":"2019-11-06T00:00:00","TransactionCode":0,"TransactionQuantity":2580.0,"TransactionPricePerSecurity":193.81,"AcquiredOrDisposed":0},{"SecurityTitle":"Common Stock","SecuritiesOwnedFollowingTransaction":4500.0,"DirectOrIndirectOwnership":0,"TransactionDate":"2019-11-07T00:00:00","TransactionCode":0,"TransactionQuantity":2500.0,"TransactionPricePerSecurity":193.83,"AcquiredOrDisposed":0},{"SecurityTitle":"Common Stock","SecuritiesOwnedFollowingTransaction":88500.0,"DirectOrIndirectOwnership":0,"TransactionDate":"2019-11-14T00:00:00","TransactionCode":0,"TransactionQuantity":1000.0,"TransactionPricePerSecurity":194.12,"AcquiredOrDisposed":0}],"AveragePerformance":{"Beginning":"2010-01-01T00:00:00","End":"2019-12-31T00:00:00","Return14":0.005609628,"Return30":0.012059174,"Return90":0.036615543,"Return180":0.07457179,"Return360":0.15470453},"PerformancesFollowingInsiderBuys":[{"Beginning":"2012-06-11T00:00:00","End":"2013-06-11T00:00:00","Return14":0.01766965,"Return30":0.033953194,"Return90":0.06269236,"Return180":0.03911644,"Return360":0.1535452},{"Beginning":"2012-11-07T00:00:00","End":"2013-11-07T00:00:00","Return14":-0.009785626,"Return30":0.027797978,"Return90":0.10248998,"Return180":0.19522657,"Return360":0.15686017},{"Beginning":"2013-10-25T00:00:00","End":"2014-10-25T00:00:00","Return14":0.023527997,"Return30":0.043680046,"Return90":0.0140618635,"Return180":0.06357879,"Return360":0.007824307},{"Beginning":"2016-02-10T00:00:00","End":"2017-02-10T00:00:00","Return14":-0.0040835254,"Return30":0.041950397,"Return90":0.12810095,"Return180":0.021458521,"Return360":0.08958301},{"Beginning":"2017-03-22T00:00:00","End":"2018-03-22T00:00:00","Return14":0.010147329,"Return30":0.03338509,"Return90":0.20089735,"Return180":0.22848615,"Return360":0.28871262},{"Beginning":"2019-11-06T00:00:00","End":"2020-11-06T00:00:00","Return14":-0.00025747248,"Return30":0.012472694,"Return90":0.11234657,"Return180":-0.051493596,"Return360":0.12480743},{"Beginning":"2019-11-06T00:00:00","End":"2020-11-06T00:00:00","Return14":-0.00025747248,"Return30":0.012472694,"Return90":0.11234657,"Return180":-0.051493596,"Return360":0.12480743},{"Beginning":"2019-11-07T00:00:00","End":"2020-11-07T00:00:00","Return14":-0.0037807433,"Return30":0.018240744,"Return90":0.117380455,"Return180":-0.059884366,"Return360":0.12887861},{"Beginning":"2019-11-14T00:00:00","End":"2020-11-14T00:00:00","Return14":0.011855783,"Return30":0.02259411,"Return90":0.12811151,"Return180":-0.07843706,"Return360":0.12701382}]}